playkit/__init__.py
playkit/api.py
playkit-0.5.4.dist-info/.DS_Store
playkit-0.5.4.dist-info/DESCRIPTION.rst
playkit-0.5.4.dist-info/METADATA
playkit-0.5.4.dist-info/RECORD
playkit-0.5.4.dist-info/WHEEL
playkit-0.5.4.dist-info/metadata.json
playkit-0.5.4.dist-info/top_level.txt
